
{
    "isNeedPre" : false,
    "isNeedPost" : false,
    "TableCodeTarget" : 4294967295,
    "TableBytesTarget" : 4294967295,
    "MainTableName"    : "ItemResolveTable",
    "TableLocations"   : [
        {
            "ExcelPath" : "ItemResolveTable.csv",
            "SheetName" : null
        }
    ],
    "Fields"           : [
        {
            "FieldName" : "ID",
            "FieldTypeName" : "int",
            "DefaultValue"  : null,
            "ForClient"     : true,
            "ForServer"     : true,
            "ClientPosID"   : 0,
            "ServerPosID"   : 0,
            "EditorPosID"   : 0,
            "ClientPosTimeStamp" : 20200708222912,
            "ServerPosTimeStamp" : 20200708222912,
            "EditorPosTimeStamp" : 20200708222912,
            "IndexType"          : 2,
            "CheckInfos"         : [
            ],
            "NeedLocal"          : false
        },
        {
            "FieldName" : "ResolveAmount",
            "FieldTypeName" : "vector<Sequence<int, 2>>",
            "DefaultValue"  : null,
            "ForClient"     : true,
            "ForServer"     : true,
            "ClientPosID"   : 1,
            "ServerPosID"   : 1,
            "EditorPosID"   : 1,
            "ClientPosTimeStamp" : 20200708222912,
            "ServerPosTimeStamp" : 20200708222912,
            "EditorPosTimeStamp" : 20200708222912,
            "IndexType"          : 0,
            "CheckInfos"         : [
            ],
            "NeedLocal"          : false
        }
    ],
    "Children"         : [
    ],
    "CheckInfos"       : [
    ],
    "ClientCacheTableFlags" : 0,
    "ServerCacheTableFlags" : 0
}