
{
    "isNeedPre" : false,
    "isNeedPost" : false,
    "TableCodeTarget" : 4294967295,
    "TableBytesTarget" : 4294967295,
    "MainTableName"    : "TdUnitTable",
    "TableLocations"   : [
        {
            "ExcelPath" : "TdUnitTable.csv",
            "SheetName" : null
        }
    ],
    "Fields"           : [
        {
            "FieldName" : "ID",
            "FieldTypeName" : "int",
            "DefaultValue"  : null,
            "ForClient"     : true,
            "ForServer"     : true,
            "ClientPosID"   : 0,
            "ServerPosID"   : 0,
            "EditorPosID"   : 0,
            "ClientPosTimeStamp" : 20190719104936,
            "ServerPosTimeStamp" : 20190719104936,
            "EditorPosTimeStamp" : 20190719104936,
            "IndexType"          : 1,
            "CheckInfos"         : [
            ],
            "NeedLocal"          : false
        },
        {
            "FieldName" : "Name",
            "FieldTypeName" : "string",
            "DefaultValue"  : null,
            "ForClient"     : true,
            "ForServer"     : false,
            "ClientPosID"   : 1,
            "ServerPosID"   : -1,
            "EditorPosID"   : 1,
            "ClientPosTimeStamp" : 20190719104936,
            "ServerPosTimeStamp" : 20190719104936,
            "EditorPosTimeStamp" : 20190719104936,
            "IndexType"          : 0,
            "CheckInfos"         : [
            ],
            "NeedLocal"          : true
        },
        {
            "FieldName" : "Desc",
            "FieldTypeName" : "string",
            "DefaultValue"  : null,
            "ForClient"     : true,
            "ForServer"     : false,
            "ClientPosID"   : 2,
            "ServerPosID"   : -1,
            "EditorPosID"   : 2,
            "ClientPosTimeStamp" : 20190719104936,
            "ServerPosTimeStamp" : 20190719104936,
            "EditorPosTimeStamp" : 20190719104936,
            "IndexType"          : 0,
            "CheckInfos"         : [
            ],
            "NeedLocal"          : true
        },
        {
            "FieldName" : "SummonCosts",
            "FieldTypeName" : "vector<Sequence<int, 3>>",
            "DefaultValue"  : null,
            "ForClient"     : true,
            "ForServer"     : true,
            "ClientPosID"   : 3,
            "ServerPosID"   : 1,
            "EditorPosID"   : 3,
            "ClientPosTimeStamp" : 20190719104936,
            "ServerPosTimeStamp" : 20190719104936,
            "EditorPosTimeStamp" : 20190719104936,
            "IndexType"          : 0,
            "CheckInfos"         : [
            ],
            "NeedLocal"          : false
        },
        {
            "FieldName" : "UpgradeCosts",
            "FieldTypeName" : "vector<Sequence<int, 2>>",
            "DefaultValue"  : null,
            "ForClient"     : true,
            "ForServer"     : true,
            "ClientPosID"   : 4,
            "ServerPosID"   : 2,
            "EditorPosID"   : 4,
            "ClientPosTimeStamp" : 20190723160537,
            "ServerPosTimeStamp" : 20190723160537,
            "EditorPosTimeStamp" : 20190723160537,
            "IndexType"          : 0,
            "CheckInfos"         : [
            ],
            "NeedLocal"          : false
        },
        {
            "FieldName" : "IconAtlas",
            "FieldTypeName" : "string",
            "DefaultValue"  : null,
            "ForClient"     : true,
            "ForServer"     : false,
            "ClientPosID"   : 5,
            "ServerPosID"   : -1,
            "EditorPosID"   : 5,
            "ClientPosTimeStamp" : 20190830112304,
            "ServerPosTimeStamp" : 20190830112304,
            "EditorPosTimeStamp" : 20190830112304,
            "IndexType"          : 0,
            "CheckInfos"         : [
            ],
            "NeedLocal"          : false
        },
        {
            "FieldName" : "IconName",
            "FieldTypeName" : "string",
            "DefaultValue"  : null,
            "ForClient"     : true,
            "ForServer"     : false,
            "ClientPosID"   : 6,
            "ServerPosID"   : -1,
            "EditorPosID"   : 6,
            "ClientPosTimeStamp" : 20190830112304,
            "ServerPosTimeStamp" : 20190830112304,
            "EditorPosTimeStamp" : 20190830112304,
            "IndexType"          : 0,
            "CheckInfos"         : [
            ],
            "NeedLocal"          : false
        }
    ],
    "Children"         : [
    ],
    "CheckInfos"       : [
    ],
    "ClientCacheTableFlags" : 0,
    "ServerCacheTableFlags" : 0
}