
{
    "isNeedPre" : false,
    "isNeedPost" : false,
    "TableCodeTarget" : 7,
    "TableBytesTarget" : 3,
    "MainTableName"    : "WheelSlotUnlock",
    "TableLocations"   : [
        {
            "ExcelPath" : "WheelSlotUnlock.csv",
            "SheetName" : null
        }
    ],
    "Fields"           : [
        {
            "FieldName" : "SlotId",
            "FieldTypeName" : "int",
            "DefaultValue"  : null,
            "ForClient"     : true,
            "ForServer"     : true,
            "ClientPosID"   : 0,
            "ServerPosID"   : 0,
            "EditorPosID"   : 0,
            "ClientPosTimeStamp" : 20200701100208,
            "ServerPosTimeStamp" : 20200701100208,
            "EditorPosTimeStamp" : 20200701100208,
            "IndexType"          : 1,
            "CheckInfos"         : null,
            "NeedLocal"          : false
        },
        {
            "FieldName" : "OpenLevel",
            "FieldTypeName" : "int",
            "DefaultValue"  : null,
            "ForClient"     : true,
            "ForServer"     : true,
            "ClientPosID"   : 1,
            "ServerPosID"   : 1,
            "EditorPosID"   : 1,
            "ClientPosTimeStamp" : 20200701100208,
            "ServerPosTimeStamp" : 20200701100208,
            "EditorPosTimeStamp" : 20200701100208,
            "IndexType"          : 0,
            "CheckInfos"         : null,
            "NeedLocal"          : false
        }
    ],
    "Children"         : [
    ],
    "CheckInfos"       : null,
    "ClientCacheTableFlags" : 0,
    "ServerCacheTableFlags" : 0
}